{
  "date" : "Thu, 13 Jun, 2024 07:18:59 +0000",
  "doco" : "For each file: start is seconds after start activity occurred. Length = milliseconds activity took",
  "files" : [
    {
      "name" : "/fsh-generated/resources/ImplementationGuide-ans.fhir.fr.sas.json",
      "size" : 10586,
      "processes" : [
        {
          "activity" : "load",
          "start" : 48,
          "length" : 14
        },
        {
          "activity" : "checkR4R4B",
          "start" : 51,
          "length" : 6
        },
        {
          "activity" : "generateNarratives",
          "start" : 51,
          "length" : 48
        },
        {
          "activity" : "validate",
          "start" : 61,
          "length" : 493
        },
        {
          "activity" : "scanForUsageStats",
          "start" : 62,
          "length" : 1
        },
        {
          "activity" : "generate1",
          "start" : 62,
          "length" : 119
        },
        {
          "activity" : "generate2",
          "start" : 72,
          "length" : 123
        },
        {
          "activity" : "generateValidationPack",
          "start" : 233,
          "length" : 5
        },
        {
          "activity" : "scanExamplesForR5",
          "start" : 263,
          "length" : 1
        }
      ]
    },
    {
      "name" : "fsh-generated/resources/Organization-ExampleOrgaCPTS.json",
      "size" : 632,
      "processes" : [
        {
          "activity" : "loadResources",
          "start" : 32,
          "length" : 14
        },
        {
          "activity" : "generateNarratives",
          "start" : 51,
          "length" : 115
        },
        {
          "activity" : "validate",
          "start" : 62,
          "length" : 10
        },
        {
          "activity" : "generate1",
          "start" : 62,
          "length" : 11
        },
        {
          "activity" : "generate2",
          "start" : 73,
          "length" : 14
        }
      ]
    },
    {
      "name" : "fsh-generated/resources/StructureDefinition-BundleAgregateur.json",
      "size" : 3151,
      "processes" : [
        {
          "activity" : "loadResources",
          "start" : 32,
          "length" : 14
        },
        {
          "activity" : "loadDepInfo",
          "start" : 48,
          "length" : 1
        },
        {
          "activity" : "load",
          "start" : 48,
          "length" : 10
        },
        {
          "activity" : "generateSnapshots",
          "start" : 48,
          "length" : 2326
        },
        {
          "activity" : "generateNarratives",
          "start" : 51,
          "length" : 87
        },
        {
          "activity" : "validate",
          "start" : 55,
          "length" : 1056
        },
        {
          "activity" : "scanForUsageStats",
          "start" : 62,
          "length" : 3
        },
        {
          "activity" : "generate1",
          "start" : 62,
          "length" : 784
        },
        {
          "activity" : "generate2",
          "start" : 73,
          "length" : 3384
        },
        {
          "activity" : "generateValidationPack",
          "start" : 233,
          "length" : 21
        },
        {
          "activity" : "scanProfilesForR5",
          "start" : 263,
          "length" : 1
        },
        {
          "activity" : "scanExamplesForR5",
          "start" : 263,
          "length" : 3
        }
      ]
    },
    {
      "name" : "fsh-generated/resources/StructureDefinition-FrAppointmentSAS.json",
      "size" : 5137,
      "processes" : [
        {
          "activity" : "loadResources",
          "start" : 32,
          "length" : 20
        },
        {
          "activity" : "load-configure",
          "start" : 48,
          "length" : 1
        },
        {
          "activity" : "load",
          "start" : 48,
          "length" : 6
        },
        {
          "activity" : "generateSnapshots",
          "start" : 50,
          "length" : 109
        },
        {
          "activity" : "generateNarratives",
          "start" : 51,
          "length" : 109
        },
        {
          "activity" : "validate",
          "start" : 56,
          "length" : 599
        },
        {
          "activity" : "checkConformanceResources",
          "start" : 61,
          "length" : 1
        },
        {
          "activity" : "scanForUsageStats",
          "start" : 62,
          "length" : 2
        },
        {
          "activity" : "generate1",
          "start" : 63,
          "length" : 606
        },
        {
          "activity" : "generate2",
          "start" : 76,
          "length" : 759
        },
        {
          "activity" : "generateValidationPack",
          "start" : 233,
          "length" : 19
        },
        {
          "activity" : "scanExamplesForR5",
          "start" : 263,
          "length" : 1
        }
      ]
    },
    {
      "name" : "fsh-generated/resources/StructureDefinition-FrLocationAgregateur.json",
      "size" : 1547,
      "processes" : [
        {
          "activity" : "loadResources",
          "start" : 32,
          "length" : 12
        },
        {
          "activity" : "scan",
          "start" : 48,
          "length" : 1
        },
        {
          "activity" : "load",
          "start" : 48,
          "length" : 5
        },
        {
          "activity" : "generateSnapshots",
          "start" : 50,
          "length" : 53
        },
        {
          "activity" : "generateNarratives",
          "start" : 51,
          "length" : 68
        },
        {
          "activity" : "validate",
          "start" : 56,
          "length" : 332
        },
        {
          "activity" : "scanForUsageStats",
          "start" : 62,
          "length" : 1
        },
        {
          "activity" : "generate1",
          "start" : 63,
          "length" : 317
        },
        {
          "activity" : "generate2",
          "start" : 77,
          "length" : 631
        },
        {
          "activity" : "generateValidationPack",
          "start" : 233,
          "length" : 10
        }
      ]
    },
    {
      "name" : "fsh-generated/resources/StructureDefinition-FrPractitionerAgregateur.json",
      "size" : 2532,
      "processes" : [
        {
          "activity" : "loadResources",
          "start" : 32,
          "length" : 12
        },
        {
          "activity" : "load",
          "start" : 48,
          "length" : 5
        },
        {
          "activity" : "generateSnapshots",
          "start" : 50,
          "length" : 113
        },
        {
          "activity" : "generateNarratives",
          "start" : 52,
          "length" : 138
        },
        {
          "activity" : "validate",
          "start" : 57,
          "length" : 1040
        },
        {
          "activity" : "scanForUsageStats",
          "start" : 62,
          "length" : 4
        },
        {
          "activity" : "generate1",
          "start" : 64,
          "length" : 779
        },
        {
          "activity" : "generate2",
          "start" : 77,
          "length" : 937
        },
        {
          "activity" : "generateValidationPack",
          "start" : 233,
          "length" : 24
        },
        {
          "activity" : "scanExamplesForR5",
          "start" : 263,
          "length" : 2
        }
      ]
    },
    {
      "name" : "fsh-generated/resources/StructureDefinition-FrPractitionerRoleExerciceAgregateur.json",
      "size" : 2585,
      "processes" : [
        {
          "activity" : "loadResources",
          "start" : 32,
          "length" : 12
        },
        {
          "activity" : "load",
          "start" : 48,
          "length" : 5
        },
        {
          "activity" : "generateSnapshots",
          "start" : 50,
          "length" : 39
        },
        {
          "activity" : "generateNarratives",
          "start" : 52,
          "length" : 47
        },
        {
          "activity" : "validate",
          "start" : 58,
          "length" : 239
        },
        {
          "activity" : "scanForUsageStats",
          "start" : 62,
          "length" : 1
        },
        {
          "activity" : "generate1",
          "start" : 64,
          "length" : 307
        },
        {
          "activity" : "generate2",
          "start" : 78,
          "length" : 416
        },
        {
          "activity" : "generateValidationPack",
          "start" : 233,
          "length" : 11
        },
        {
          "activity" : "scanExamplesForR5",
          "start" : 263,
          "length" : 1
        }
      ]
    },
    {
      "name" : "fsh-generated/resources/StructureDefinition-FrScheduleAgregateur.json",
      "size" : 1159,
      "processes" : [
        {
          "activity" : "loadResources",
          "start" : 32,
          "length" : 12
        },
        {
          "activity" : "load",
          "start" : 48,
          "length" : 2
        },
        {
          "activity" : "generateSnapshots",
          "start" : 50,
          "length" : 27
        },
        {
          "activity" : "generateNarratives",
          "start" : 52,
          "length" : 28
        },
        {
          "activity" : "validate",
          "start" : 58,
          "length" : 120
        },
        {
          "activity" : "generate1",
          "start" : 65,
          "length" : 144
        },
        {
          "activity" : "generate2",
          "start" : 79,
          "length" : 213
        },
        {
          "activity" : "generateValidationPack",
          "start" : 233,
          "length" : 4
        }
      ]
    },
    {
      "name" : "fsh-generated/resources/StructureDefinition-FrSlotAgregateur.json",
      "size" : 4435,
      "processes" : [
        {
          "activity" : "loadResources",
          "start" : 32,
          "length" : 12
        },
        {
          "activity" : "load",
          "start" : 48,
          "length" : 5
        },
        {
          "activity" : "generateSnapshots",
          "start" : 50,
          "length" : 33
        },
        {
          "activity" : "generateNarratives",
          "start" : 52,
          "length" : 113
        },
        {
          "activity" : "validate",
          "start" : 58,
          "length" : 220
        },
        {
          "activity" : "scanForUsageStats",
          "start" : 62,
          "length" : 1
        },
        {
          "activity" : "generate1",
          "start" : 65,
          "length" : 269
        },
        {
          "activity" : "generate2",
          "start" : 79,
          "length" : 283
        },
        {
          "activity" : "generateValidationPack",
          "start" : 233,
          "length" : 9
        }
      ]
    },
    {
      "name" : "fsh-generated/resources/StructureDefinition-sas-cpts-bundle-aggregator.json",
      "size" : 5092,
      "processes" : [
        {
          "activity" : "loadResources",
          "start" : 32,
          "length" : 12
        },
        {
          "activity" : "load",
          "start" : 48,
          "length" : 5
        },
        {
          "activity" : "generateSnapshots",
          "start" : 50,
          "length" : 228
        },
        {
          "activity" : "generateNarratives",
          "start" : 52,
          "length" : 65
        },
        {
          "activity" : "validate",
          "start" : 58,
          "length" : 800
        },
        {
          "activity" : "checkConformanceResources",
          "start" : 61,
          "length" : 1
        },
        {
          "activity" : "scanForUsageStats",
          "start" : 62,
          "length" : 4
        },
        {
          "activity" : "generate1",
          "start" : 65,
          "length" : 916
        },
        {
          "activity" : "generate2",
          "start" : 79,
          "length" : 1621
        },
        {
          "activity" : "generateValidationPack",
          "start" : 233,
          "length" : 30
        },
        {
          "activity" : "scanExamplesForR5",
          "start" : 263,
          "length" : 2
        }
      ]
    },
    {
      "name" : "fsh-generated/resources/StructureDefinition-sas-cpts-healthcareservice-aggregator.json",
      "size" : 1083,
      "processes" : [
        {
          "activity" : "loadResources",
          "start" : 32,
          "length" : 11
        },
        {
          "activity" : "load",
          "start" : 48,
          "length" : 3
        },
        {
          "activity" : "generateSnapshots",
          "start" : 51,
          "length" : 36
        },
        {
          "activity" : "generateNarratives",
          "start" : 52,
          "length" : 26
        },
        {
          "activity" : "validate",
          "start" : 59,
          "length" : 200
        },
        {
          "activity" : "scanForUsageStats",
          "start" : 62,
          "length" : 1
        },
        {
          "activity" : "generate1",
          "start" : 66,
          "length" : 250
        },
        {
          "activity" : "generate2",
          "start" : 81,
          "length" : 516
        },
        {
          "activity" : "generateValidationPack",
          "start" : 233,
          "length" : 9
        }
      ]
    },
    {
      "name" : "fsh-generated/resources/StructureDefinition-sas-cpts-organization-aggregator.json",
      "size" : 1578,
      "processes" : [
        {
          "activity" : "loadResources",
          "start" : 32,
          "length" : 12
        },
        {
          "activity" : "load",
          "start" : 48,
          "length" : 3
        },
        {
          "activity" : "generateSnapshots",
          "start" : 51,
          "length" : 52
        },
        {
          "activity" : "generateNarratives",
          "start" : 52,
          "length" : 21
        },
        {
          "activity" : "validate",
          "start" : 59,
          "length" : 236
        },
        {
          "activity" : "scanForUsageStats",
          "start" : 62,
          "length" : 1
        },
        {
          "activity" : "generate1",
          "start" : 66,
          "length" : 378
        },
        {
          "activity" : "generate2",
          "start" : 81,
          "length" : 584
        },
        {
          "activity" : "generateValidationPack",
          "start" : 233,
          "length" : 12
        },
        {
          "activity" : "scanProfilesForR5",
          "start" : 263,
          "length" : 1
        },
        {
          "activity" : "scanExamplesForR5",
          "start" : 263,
          "length" : 1
        }
      ]
    },
    {
      "name" : "fsh-generated/resources/StructureDefinition-sas-cpts-slot-aggregator.json",
      "size" : 4711,
      "processes" : [
        {
          "activity" : "loadResources",
          "start" : 32,
          "length" : 13
        },
        {
          "activity" : "load",
          "start" : 48,
          "length" : 4
        },
        {
          "activity" : "generateSnapshots",
          "start" : 51,
          "length" : 25
        },
        {
          "activity" : "generateNarratives",
          "start" : 52,
          "length" : 34
        },
        {
          "activity" : "validate",
          "start" : 59,
          "length" : 192
        },
        {
          "activity" : "scanForUsageStats",
          "start" : 62,
          "length" : 1
        },
        {
          "activity" : "generate1",
          "start" : 67,
          "length" : 394
        },
        {
          "activity" : "generate2",
          "start" : 82,
          "length" : 307
        },
        {
          "activity" : "generateValidationPack",
          "start" : 233,
          "length" : 12
        }
      ]
    },
    {
      "name" : "fsh-generated/resources/StructureDefinition-sas-cpts-slot-servicetype-aggregator.json",
      "size" : 2084,
      "processes" : [
        {
          "activity" : "loadResources",
          "start" : 32,
          "length" : 12
        },
        {
          "activity" : "load-configure",
          "start" : 48,
          "length" : 1
        },
        {
          "activity" : "load",
          "start" : 48,
          "length" : 4
        },
        {
          "activity" : "generateSnapshots",
          "start" : 51,
          "length" : 12
        },
        {
          "activity" : "generateNarratives",
          "start" : 52,
          "length" : 7
        },
        {
          "activity" : "validate",
          "start" : 60,
          "length" : 29
        },
        {
          "activity" : "generate1",
          "start" : 67,
          "length" : 60
        },
        {
          "activity" : "generate2",
          "start" : 82,
          "length" : 76
        },
        {
          "activity" : "generateValidationPack",
          "start" : 233,
          "length" : 1
        },
        {
          "activity" : "scanExamplesForR5",
          "start" : 263,
          "length" : 1
        }
      ]
    },
    {
      "name" : "fsh-generated/resources/StructureDefinition-sas-sos-appointment.json",
      "size" : 3923,
      "processes" : [
        {
          "activity" : "loadResources",
          "start" : 32,
          "length" : 14
        },
        {
          "activity" : "load",
          "start" : 48,
          "length" : 5
        },
        {
          "activity" : "generateSnapshots",
          "start" : 51,
          "length" : 63
        },
        {
          "activity" : "generateNarratives",
          "start" : 52,
          "length" : 17
        },
        {
          "activity" : "validate",
          "start" : 60,
          "length" : 231
        },
        {
          "activity" : "scanForUsageStats",
          "start" : 62,
          "length" : 2
        },
        {
          "activity" : "generate1",
          "start" : 67,
          "length" : 422
        },
        {
          "activity" : "generate2",
          "start" : 82,
          "length" : 294
        },
        {
          "activity" : "makeDependencies",
          "start" : 91,
          "length" : 1
        },
        {
          "activity" : "generateValidationPack",
          "start" : 233,
          "length" : 13
        }
      ]
    },
    {
      "name" : "fsh-generated/resources/StructureDefinition-sas-sos-bundle-aggregator.json",
      "size" : 3769,
      "processes" : [
        {
          "activity" : "loadResources",
          "start" : 32,
          "length" : 12
        },
        {
          "activity" : "load",
          "start" : 48,
          "length" : 4
        },
        {
          "activity" : "generateSnapshots",
          "start" : 51,
          "length" : 119
        },
        {
          "activity" : "generateNarratives",
          "start" : 52,
          "length" : 30
        },
        {
          "activity" : "validate",
          "start" : 60,
          "length" : 408
        },
        {
          "activity" : "checkConformanceResources",
          "start" : 61,
          "length" : 1
        },
        {
          "activity" : "scanForUsageStats",
          "start" : 62,
          "length" : 2
        },
        {
          "activity" : "generate1",
          "start" : 67,
          "length" : 677
        },
        {
          "activity" : "generate2",
          "start" : 83,
          "length" : 687
        },
        {
          "activity" : "generateValidationPack",
          "start" : 233,
          "length" : 21
        },
        {
          "activity" : "scanExamplesForR5",
          "start" : 263,
          "length" : 1
        }
      ]
    },
    {
      "name" : "fsh-generated/resources/StructureDefinition-sas-sos-location-aggregator.json",
      "size" : 1954,
      "processes" : [
        {
          "activity" : "loadResources",
          "start" : 32,
          "length" : 12
        },
        {
          "activity" : "load",
          "start" : 48,
          "length" : 5
        },
        {
          "activity" : "generateSnapshots",
          "start" : 51,
          "length" : 36
        },
        {
          "activity" : "generateNarratives",
          "start" : 52,
          "length" : 17
        },
        {
          "activity" : "validate",
          "start" : 60,
          "length" : 219
        },
        {
          "activity" : "scanForUsageStats",
          "start" : 62,
          "length" : 1
        },
        {
          "activity" : "generate1",
          "start" : 68,
          "length" : 353
        },
        {
          "activity" : "generate2",
          "start" : 83,
          "length" : 289
        },
        {
          "activity" : "generateValidationPack",
          "start" : 233,
          "length" : 10
        },
        {
          "activity" : "scanExamplesForR5",
          "start" : 263,
          "length" : 1
        }
      ]
    },
    {
      "name" : "fsh-generated/resources/StructureDefinition-sas-sos-organization-aggregator.json",
      "size" : 1816,
      "processes" : [
        {
          "activity" : "loadResources",
          "start" : 32,
          "length" : 11
        },
        {
          "activity" : "load",
          "start" : 48,
          "length" : 3
        },
        {
          "activity" : "generateSnapshots",
          "start" : 51,
          "length" : 44
        },
        {
          "activity" : "generateNarratives",
          "start" : 52,
          "length" : 16
        },
        {
          "activity" : "validate",
          "start" : 60,
          "length" : 291
        },
        {
          "activity" : "scanForUsageStats",
          "start" : 62,
          "length" : 2
        },
        {
          "activity" : "generate1",
          "start" : 68,
          "length" : 387
        },
        {
          "activity" : "generate2",
          "start" : 84,
          "length" : 371
        },
        {
          "activity" : "generateValidationPack",
          "start" : 233,
          "length" : 12
        },
        {
          "activity" : "scanExamplesForR5",
          "start" : 263,
          "length" : 1
        }
      ]
    },
    {
      "name" : "fsh-generated/resources/StructureDefinition-sas-sos-schedule-aggregator.json",
      "size" : 904,
      "processes" : [
        {
          "activity" : "loadResources",
          "start" : 32,
          "length" : 7
        },
        {
          "activity" : "load",
          "start" : 48,
          "length" : 3
        },
        {
          "activity" : "generateSnapshots",
          "start" : 51,
          "length" : 30
        },
        {
          "activity" : "generateNarratives",
          "start" : 52,
          "length" : 8
        },
        {
          "activity" : "validate",
          "start" : 61,
          "length" : 165
        },
        {
          "activity" : "generate1",
          "start" : 69,
          "length" : 170
        },
        {
          "activity" : "generate2",
          "start" : 84,
          "length" : 140
        },
        {
          "activity" : "generateValidationPack",
          "start" : 233,
          "length" : 5
        }
      ]
    },
    {
      "name" : "fsh-generated/resources/StructureDefinition-sas-sos-slot-aggregator.json",
      "size" : 1781,
      "processes" : [
        {
          "activity" : "loadResources",
          "start" : 32,
          "length" : 3
        },
        {
          "activity" : "load",
          "start" : 48,
          "length" : 3
        },
        {
          "activity" : "generateSnapshots",
          "start" : 51,
          "length" : 32
        },
        {
          "activity" : "generateNarratives",
          "start" : 52,
          "length" : 13
        },
        {
          "activity" : "validate",
          "start" : 61,
          "length" : 101
        },
        {
          "activity" : "scanForUsageStats",
          "start" : 62,
          "length" : 1
        },
        {
          "activity" : "generate1",
          "start" : 69,
          "length" : 217
        },
        {
          "activity" : "generate2",
          "start" : 84,
          "length" : 172
        },
        {
          "activity" : "generateValidationPack",
          "start" : 233,
          "length" : 6
        }
      ]
    },
    {
      "name" : "fsh-generated/resources/ValueSet-sas-cpts-valueset-typecreneau.json",
      "size" : 1015,
      "processes" : [
        {
          "activity" : "loadResources",
          "start" : 32,
          "length" : 2
        },
        {
          "activity" : "load",
          "start" : 48,
          "length" : 9
        },
        {
          "activity" : "checkR4R4B",
          "start" : 51,
          "length" : 1
        },
        {
          "activity" : "generateNarratives",
          "start" : 52,
          "length" : 588
        },
        {
          "activity" : "validate",
          "start" : 54,
          "length" : 592
        },
        {
          "activity" : "generate1",
          "start" : 69,
          "length" : 12
        },
        {
          "activity" : "generate2",
          "start" : 84,
          "length" : 3129
        }
      ]
    },
    {
      "name" : "fsh-generated/resources/ValueSet-sas-sos-valueset-appointmentreason.json",
      "size" : 725,
      "processes" : [
        {
          "activity" : "loadResources",
          "start" : 32,
          "length" : 2
        },
        {
          "activity" : "load",
          "start" : 48,
          "length" : 4
        },
        {
          "activity" : "generateNarratives",
          "start" : 53,
          "length" : 3
        },
        {
          "activity" : "validate",
          "start" : 54,
          "length" : 11
        },
        {
          "activity" : "generate1",
          "start" : 69,
          "length" : 15
        },
        {
          "activity" : "generate2",
          "start" : 87,
          "length" : 62
        },
        {
          "activity" : "generateValidationPack",
          "start" : 233,
          "length" : 1
        }
      ]
    },
    {
      "name" : "fsh-generated/resources/ValueSet-sas-sos-valueset-participant-status.json",
      "size" : 753,
      "processes" : [
        {
          "activity" : "loadResources",
          "start" : 32,
          "length" : 2
        },
        {
          "activity" : "load",
          "start" : 48,
          "length" : 3
        },
        {
          "activity" : "generateNarratives",
          "start" : 53,
          "length" : 2
        },
        {
          "activity" : "validate",
          "start" : 54,
          "length" : 9
        },
        {
          "activity" : "generate1",
          "start" : 69,
          "length" : 13
        },
        {
          "activity" : "generate2",
          "start" : 87,
          "length" : 51
        }
      ]
    },
    {
      "name" : "fsh-generated/resources/ValueSet-sas-sos-valueset-typeconsultation.json",
      "size" : 779,
      "processes" : [
        {
          "activity" : "loadResources",
          "start" : 32,
          "length" : 2
        },
        {
          "activity" : "load",
          "start" : 48,
          "length" : 3
        },
        {
          "activity" : "generateNarratives",
          "start" : 53,
          "length" : 5
        },
        {
          "activity" : "validate",
          "start" : 54,
          "length" : 10
        },
        {
          "activity" : "generate1",
          "start" : 69,
          "length" : 15
        },
        {
          "activity" : "generate2",
          "start" : 87,
          "length" : 52
        }
      ]
    },
    {
      "name" : "fsh-generated/resources/ValueSet-sas-sos-valueset-typecreneau.json",
      "size" : 769,
      "processes" : [
        {
          "activity" : "loadResources",
          "start" : 32,
          "length" : 3
        },
        {
          "activity" : "load",
          "start" : 48,
          "length" : 5
        },
        {
          "activity" : "generateNarratives",
          "start" : 53,
          "length" : 481
        },
        {
          "activity" : "validate",
          "start" : 54,
          "length" : 5
        },
        {
          "activity" : "generate1",
          "start" : 69,
          "length" : 13
        },
        {
          "activity" : "generate2",
          "start" : 88,
          "length" : 546
        },
        {
          "activity" : "generateValidationPack",
          "start" : 233,
          "length" : 1
        }
      ]
    },
    {
      "name" : "fsh-generated/resources/ValueSet-sas-sos-valueset-typeidentifiant.json",
      "size" : 703,
      "processes" : [
        {
          "activity" : "loadResources",
          "start" : 32,
          "length" : 2
        },
        {
          "activity" : "load-configure",
          "start" : 48,
          "length" : 1
        },
        {
          "activity" : "load",
          "start" : 48,
          "length" : 4
        },
        {
          "activity" : "generateNarratives",
          "start" : 53,
          "length" : 5
        },
        {
          "activity" : "validate",
          "start" : 54,
          "length" : 7
        },
        {
          "activity" : "generate1",
          "start" : 69,
          "length" : 12
        },
        {
          "activity" : "generate2",
          "start" : 88,
          "length" : 33
        }
      ]
    },
    {
      "name" : "fsh-generated/resources/ValueSet-sas-valueset-categorieetablissement.json",
      "size" : 674,
      "processes" : [
        {
          "activity" : "loadResources",
          "start" : 32,
          "length" : 2
        },
        {
          "activity" : "load",
          "start" : 48,
          "length" : 3
        },
        {
          "activity" : "generateNarratives",
          "start" : 53,
          "length" : 553
        },
        {
          "activity" : "validate",
          "start" : 54,
          "length" : 143
        },
        {
          "activity" : "generate1",
          "start" : 69,
          "length" : 12
        },
        {
          "activity" : "generate2",
          "start" : 88,
          "length" : 529
        }
      ]
    }
  ]
}
